ordeq_joblib/__init__.py
ordeq_joblib/_version.py
ordeq_joblib/joblib.py
ordeq_joblib/py.typed
ordeq_joblib-1.0.2.dist-info/licenses/LICENSE
ordeq_joblib-1.0.2.dist-info/METADATA
ordeq_joblib-1.0.2.dist-info/WHEEL
ordeq_joblib-1.0.2.dist-info/top_level.txt
ordeq_joblib-1.0.2.dist-info/RECORD
