Metadata-Version: 2.4
Name: ordeq_joblib
Version: 1.0.2
Summary: Joblib integration for Ordeq
Author: Niels Neerhoff, Simon Brugman
Maintainer: Niels Neerhoff, Simon Brugman
License-Expression: MIT
Requires-Python: >=3.10
License-File: LICENSE
Requires-Dist: ordeq>=1.2.0
Requires-Dist: joblib
Dynamic: license-file
